data_processing/create_realization.py
data_processing/dask_utils.py
data_processing/dataset_utils.py
data_processing/datasets.py
data_processing/file_paths.py
data_processing/forcings.py
data_processing/gpkg_utils.py
data_processing/graph_utils.py
data_processing/s3fs_utils.py
data_processing/subset.py
data_sources/cfe-nowpm-realization-template.json
data_sources/cfe-template.ini
data_sources/forcing_template.nc
data_sources/lstm-catchment-template.yml
data_sources/lstm-realization-template.json
data_sources/lstm-rust-realization-template.json
data_sources/ngen-routing-template.yaml
data_sources/noah-owp-modular-init.namelist.input
data_sources/source_validation.py
data_sources/template.sql
data_sources/triggers.sql
map_app/__init__.py
map_app/__main__.py
map_app/views.py
map_app/static/css/console.css
map_app/static/css/main.css
map_app/static/css/toggle.css
map_app/static/js/console.js
map_app/static/js/data_processing.js
map_app/static/js/main.js
map_app/static/resources/loading.gif
map_app/static/resources/screenshot.jpg
map_app/templates/index.html
ngiab_data_cli/__main__.py
ngiab_data_cli/arguments.py
ngiab_data_cli/custom_logging.py
ngiab_data_cli/forcing_cli.py
ngiab_data_preprocess-4.6.7.dist-info/licenses/LICENSE
ngiab_data_preprocess-4.6.7.dist-info/METADATA
ngiab_data_preprocess-4.6.7.dist-info/WHEEL
ngiab_data_preprocess-4.6.7.dist-info/entry_points.txt
ngiab_data_preprocess-4.6.7.dist-info/top_level.txt
ngiab_data_preprocess-4.6.7.dist-info/RECORD
