Metadata-Version: 2.4
Name: ngiab_data_preprocess
Version: 4.6.7
Summary: Graphical Tools for creating Next Gen Water model input data.
Author-email: Josh Cunningham <jcunningham8@ua.edu>
Project-URL: Homepage, https://github.com/CIROH-UA/NGIAB_data_preprocess
Project-URL: Issues, https://github.com/CIROH-UA/NGIAB_data_preprocess/issues
Classifier: Programming Language :: Python :: 3
Classifier: License :: OSI Approved :: MIT License
Classifier: Operating System :: OS Independent
Requires-Python: >=3.10
License-File: LICENSE
Requires-Dist: pyogrio>=0.7.2
Requires-Dist: pyproj>=3.6.1
Requires-Dist: Flask==3.0.2
Requires-Dist: geopandas>=1.0.0
Requires-Dist: requests==2.32.4
Requires-Dist: igraph==0.11.4
Requires-Dist: s3fs==2024.3.1
Requires-Dist: xarray==2024.2.0
Requires-Dist: zarr==2.17.1
Requires-Dist: netCDF4<1.7.3,>=1.6.5
Requires-Dist: dask==2024.4.1
Requires-Dist: dask[distributed]==2024.4.1
Requires-Dist: exactextract==0.2.0
Requires-Dist: numpy>=1.26.4
Requires-Dist: tqdm==4.66.4
Requires-Dist: rich==13.7.1
Requires-Dist: colorama==0.4.6
Requires-Dist: bokeh==3.5.1
Requires-Dist: boto3
Requires-Dist: numcodecs<0.16.0
Requires-Dist: scipy>=1.15.3
Provides-Extra: eval
Requires-Dist: ngiab_eval; extra == "eval"
Provides-Extra: plot
Requires-Dist: ngiab_eval[plot]; extra == "plot"
Dynamic: license-file
